maxpress/__init__.py
maxpress/__main__.py
maxpress/renderer.py
maxpress/css/default.css
maxpress/less/default.less
maxpress/less/styles.less
mistletoe_contrib/__init__.py
mistletoe_contrib/mathjax.py
mistletoe_contrib/pygments_renderer.py
mistletoe_contrib/text_renderer.py
mistletoe_contrib/toc_renderer.py
maxpress-0.5.5.dist-info/LICENSE
maxpress-0.5.5.dist-info/METADATA
maxpress-0.5.5.dist-info/WHEEL
maxpress-0.5.5.dist-info/entry_points.txt
maxpress-0.5.5.dist-info/top_level.txt
maxpress-0.5.5.dist-info/RECORD
