Metadata-Version: 2.1
Name: maxpress
Version: 0.5.5
Summary: convert markdown wechat html. 转换Markdown文章为公众号可粘贴的HTML格式.
Home-page: https://github.com/weaming/maxpress
Author: weaming
Author-email: garden.yuen@gmail.com
License: UNKNOWN
Project-URL: Source, https://github.com/weaming/maxpress
Project-URL: Bug Reports, https://github.com/weaming/maxpress
Keywords: math
Platform: UNKNOWN
Requires-Dist: six (>=1.10.0)
Requires-Dist: premailer (>=3.0.1)
Requires-Dist: lesscpy (>=0.12.0)
Requires-Dist: Pygments (>=2.6.1)
Requires-Dist: emoji
Requires-Dist: pangu
Requires-Dist: mistletoe
